<?xml version="1.0" encoding="UTF-8" standalone="yes"?>
<p:sld xmlns:a="http://schemas.openxmlformats.org/drawingml/2006/main" xmlns:r="http://schemas.openxmlformats.org/officeDocument/2006/relationships" xmlns:p="http://schemas.openxmlformats.org/presentationml/2006/main"><p:cSld><p:spTree><p:nvGrpSpPr><p:cNvPr id="1" name=""/><p:cNvGrpSpPr/><p:nvPr/></p:nvGrpSpPr><p:grpSpPr><a:xfrm><a:off x="0" y="0"/><a:ext cx="0" cy="0"/><a:chOff x="0" y="0"/><a:chExt cx="0" cy="0"/></a:xfrm></p:grpSpPr><p:sp><p:nvSpPr><p:cNvPr id="4" name="Rectangle 3"/><p:cNvSpPr/><p:nvPr/></p:nvSpPr><p:spPr><a:xfrm><a:off x="6923314" y="1114413"/><a:ext cx="4859383" cy="5456204"/></a:xfrm><a:prstGeom prst="rect"><a:avLst/></a:prstGeom></p:spPr><p:style><a:lnRef idx="2"><a:schemeClr val="accent6"/></a:lnRef><a:fillRef idx="1"><a:schemeClr val="lt1"/></a:fillRef><a:effectRef idx="0"><a:schemeClr val="accent6"/></a:effectRef><a:fontRef idx="minor"><a:schemeClr val="dk1"/></a:fontRef></p:style><p:txBody><a:bodyPr rtlCol="0" anchor="ctr"/><a:lstStyle/><a:p><a:pPr algn="ctr"/><a:endParaRPr lang="en-US"/></a:p></p:txBody></p:sp><p:cxnSp><p:nvCxnSpPr><p:cNvPr id="3" name="Straight Connector 2"/><p:cNvCxnSpPr/><p:nvPr/></p:nvCxnSpPr><p:spPr><a:xfrm flipH="1"><a:off x="2164977" y="1721224"/><a:ext cx="685799" cy="699247"/></a:xfrm><a:prstGeom prst="line"><a:avLst/></a:prstGeom></p:spPr><p:style><a:lnRef idx="1"><a:schemeClr val="accent1"/></a:lnRef><a:fillRef idx="0"><a:schemeClr val="accent1"/></a:fillRef><a:effectRef idx="0"><a:schemeClr val="accent1"/></a:effectRef><a:fontRef idx="minor"><a:schemeClr val="tx1"/></a:fontRef></p:style></p:cxnSp><p:cxnSp><p:nvCxnSpPr><p:cNvPr id="5" name="Straight Connector 4"/><p:cNvCxnSpPr/><p:nvPr/></p:nvCxnSpPr><p:spPr><a:xfrm><a:off x="3847161" y="1701514"/><a:ext cx="685799" cy="699247"/></a:xfrm><a:prstGeom prst="line"><a:avLst/></a:prstGeom></p:spPr><p:style><a:lnRef idx="1"><a:schemeClr val="accent1"/></a:lnRef><a:fillRef idx="0"><a:schemeClr val="accent1"/></a:fillRef><a:effectRef idx="0"><a:schemeClr val="accent1"/></a:effectRef><a:fontRef idx="minor"><a:schemeClr val="tx1"/></a:fontRef></p:style></p:cxnSp><p:sp><p:nvSpPr><p:cNvPr id="6" name="TextBox 5"/><p:cNvSpPr txBox="1"/><p:nvPr/></p:nvSpPr><p:spPr><a:xfrm><a:off x="4158609" y="1619036"/><a:ext cx="491225" cy="369332"/></a:xfrm><a:prstGeom prst="rect"><a:avLst/></a:prstGeom><a:noFill/></p:spPr><p:txBody><a:bodyPr wrap="none" rtlCol="0"><a:spAutoFit/></a:bodyPr><a:lstStyle/><a:p><a:r><a:rPr lang="en-US" dirty="0"><a:solidFill><a:srgbClr val="7030A0"/></a:solidFill></a:rPr><a:t>yes</a:t></a:r></a:p></p:txBody></p:sp><p:sp><p:nvSpPr><p:cNvPr id="7" name="TextBox 6"/><p:cNvSpPr txBox="1"/><p:nvPr/></p:nvSpPr><p:spPr><a:xfrm><a:off x="2016651" y="1761564"/><a:ext cx="428322" cy="369332"/></a:xfrm><a:prstGeom prst="rect"><a:avLst/></a:prstGeom><a:noFill/></p:spPr><p:txBody><a:bodyPr wrap="none" rtlCol="0"><a:spAutoFit/></a:bodyPr><a:lstStyle/><a:p><a:r><a:rPr lang="en-US" dirty="0"><a:solidFill><a:srgbClr val="7030A0"/></a:solidFill></a:rPr><a:t>no</a:t></a:r></a:p></p:txBody></p:sp><p:sp><p:nvSpPr><p:cNvPr id="8" name="TextBox 7"/><p:cNvSpPr txBox="1"/><p:nvPr/></p:nvSpPr><p:spPr><a:xfrm><a:off x="2861963" y="1114413"/><a:ext cx="1003801" cy="461665"/></a:xfrm><a:prstGeom prst="rect"><a:avLst/></a:prstGeom><a:noFill/></p:spPr><p:txBody><a:bodyPr wrap="none" rtlCol="0"><a:spAutoFit/></a:bodyPr><a:lstStyle/><a:p><a:r><a:rPr lang="en-US" sz="2400" dirty="0"/><a:t>X = 3 ?</a:t></a:r></a:p></p:txBody></p:sp><p:cxnSp><p:nvCxnSpPr><p:cNvPr id="9" name="Straight Connector 8"/><p:cNvCxnSpPr/><p:nvPr/></p:nvCxnSpPr><p:spPr><a:xfrm flipH="1"><a:off x="1182307" y="3024663"/><a:ext cx="685799" cy="699247"/></a:xfrm><a:prstGeom prst="line"><a:avLst/></a:prstGeom></p:spPr><p:style><a:lnRef idx="1"><a:schemeClr val="accent1"/></a:lnRef><a:fillRef idx="0"><a:schemeClr val="accent1"/></a:fillRef><a:effectRef idx="0"><a:schemeClr val="accent1"/></a:effectRef><a:fontRef idx="minor"><a:schemeClr val="tx1"/></a:fontRef></p:style></p:cxnSp><p:cxnSp><p:nvCxnSpPr><p:cNvPr id="10" name="Straight Connector 9"/><p:cNvCxnSpPr/><p:nvPr/></p:nvCxnSpPr><p:spPr><a:xfrm><a:off x="2123602" y="3024662"/><a:ext cx="685799" cy="699247"/></a:xfrm><a:prstGeom prst="line"><a:avLst/></a:prstGeom></p:spPr><p:style><a:lnRef idx="1"><a:schemeClr val="accent1"/></a:lnRef><a:fillRef idx="0"><a:schemeClr val="accent1"/></a:fillRef><a:effectRef idx="0"><a:schemeClr val="accent1"/></a:effectRef><a:fontRef idx="minor"><a:schemeClr val="tx1"/></a:fontRef></p:style></p:cxnSp><p:sp><p:nvSpPr><p:cNvPr id="11" name="TextBox 10"/><p:cNvSpPr txBox="1"/><p:nvPr/></p:nvSpPr><p:spPr><a:xfrm><a:off x="2573672" y="3004953"/><a:ext cx="491225" cy="369332"/></a:xfrm><a:prstGeom prst="rect"><a:avLst/></a:prstGeom><a:noFill/></p:spPr><p:txBody><a:bodyPr wrap="none" rtlCol="0"><a:spAutoFit/></a:bodyPr><a:lstStyle/><a:p><a:r><a:rPr lang="en-US" dirty="0"><a:solidFill><a:srgbClr val="7030A0"/></a:solidFill></a:rPr><a:t>yes</a:t></a:r></a:p></p:txBody></p:sp><p:sp><p:nvSpPr><p:cNvPr id="12" name="TextBox 11"/><p:cNvSpPr txBox="1"/><p:nvPr/></p:nvSpPr><p:spPr><a:xfrm><a:off x="1033981" y="3065003"/><a:ext cx="428322" cy="369332"/></a:xfrm><a:prstGeom prst="rect"><a:avLst/></a:prstGeom><a:noFill/></p:spPr><p:txBody><a:bodyPr wrap="none" rtlCol="0"><a:spAutoFit/></a:bodyPr><a:lstStyle/><a:p><a:r><a:rPr lang="en-US" dirty="0"><a:solidFill><a:srgbClr val="7030A0"/></a:solidFill></a:rPr><a:t>no</a:t></a:r></a:p></p:txBody></p:sp><p:sp><p:nvSpPr><p:cNvPr id="13" name="TextBox 12"/><p:cNvSpPr txBox="1"/><p:nvPr/></p:nvSpPr><p:spPr><a:xfrm><a:off x="1663076" y="2460810"/><a:ext cx="1003801" cy="461665"/></a:xfrm><a:prstGeom prst="rect"><a:avLst/></a:prstGeom><a:noFill/></p:spPr><p:txBody><a:bodyPr wrap="none" rtlCol="0"><a:spAutoFit/></a:bodyPr><a:lstStyle/><a:p><a:r><a:rPr lang="en-US" sz="2400" dirty="0"/><a:t>Y &gt; 3 ?</a:t></a:r></a:p></p:txBody></p:sp><p:sp><p:nvSpPr><p:cNvPr id="18" name="TextBox 17"/><p:cNvSpPr txBox="1"/><p:nvPr/></p:nvSpPr><p:spPr><a:xfrm><a:off x="2307500" y="3734634"/><a:ext cx="1143262" cy="461665"/></a:xfrm><a:prstGeom prst="rect"><a:avLst/></a:prstGeom><a:noFill/></p:spPr><p:txBody><a:bodyPr wrap="none" rtlCol="0"><a:spAutoFit/></a:bodyPr><a:lstStyle/><a:p><a:r><a:rPr lang="en-US" sz="2400" dirty="0"/><a:t>Z &lt; 10 ?</a:t></a:r></a:p></p:txBody></p:sp><p:cxnSp><p:nvCxnSpPr><p:cNvPr id="20" name="Straight Connector 19"/><p:cNvCxnSpPr/><p:nvPr/></p:nvCxnSpPr><p:spPr><a:xfrm><a:off x="5065521" y="3024662"/><a:ext cx="685799" cy="699247"/></a:xfrm><a:prstGeom prst="line"><a:avLst/></a:prstGeom></p:spPr><p:style><a:lnRef idx="1"><a:schemeClr val="accent1"/></a:lnRef><a:fillRef idx="0"><a:schemeClr val="accent1"/></a:fillRef><a:effectRef idx="0"><a:schemeClr val="accent1"/></a:effectRef><a:fontRef idx="minor"><a:schemeClr val="tx1"/></a:fontRef></p:style></p:cxnSp><p:sp><p:nvSpPr><p:cNvPr id="21" name="TextBox 20"/><p:cNvSpPr txBox="1"/><p:nvPr/></p:nvSpPr><p:spPr><a:xfrm><a:off x="5515591" y="3004953"/><a:ext cx="491225" cy="369332"/></a:xfrm><a:prstGeom prst="rect"><a:avLst/></a:prstGeom><a:noFill/></p:spPr><p:txBody><a:bodyPr wrap="none" rtlCol="0"><a:spAutoFit/></a:bodyPr><a:lstStyle/><a:p><a:r><a:rPr lang="en-US" dirty="0"><a:solidFill><a:srgbClr val="7030A0"/></a:solidFill></a:rPr><a:t>yes</a:t></a:r></a:p></p:txBody></p:sp><p:sp><p:nvSpPr><p:cNvPr id="23" name="TextBox 22"/><p:cNvSpPr txBox="1"/><p:nvPr/></p:nvSpPr><p:spPr><a:xfrm><a:off x="4604995" y="2460810"/><a:ext cx="1003801" cy="461665"/></a:xfrm><a:prstGeom prst="rect"><a:avLst/></a:prstGeom><a:noFill/></p:spPr><p:txBody><a:bodyPr wrap="none" rtlCol="0"><a:spAutoFit/></a:bodyPr><a:lstStyle/><a:p><a:r><a:rPr lang="en-US" sz="2400" dirty="0"/><a:t>Y &gt; 3 ?</a:t></a:r></a:p></p:txBody></p:sp><p:sp><p:nvSpPr><p:cNvPr id="24" name="TextBox 23"/><p:cNvSpPr txBox="1"/><p:nvPr/></p:nvSpPr><p:spPr><a:xfrm><a:off x="707504" y="3685310"/><a:ext cx="908710" cy="369332"/></a:xfrm><a:prstGeom prst="rect"><a:avLst/></a:prstGeom><a:noFill/></p:spPr><p:txBody><a:bodyPr wrap="none" rtlCol="0"><a:spAutoFit/></a:bodyPr><a:lstStyle/><a:p><a:r><a:rPr lang="en-US" b="1" dirty="0"><a:solidFill><a:srgbClr val="FF0000"/></a:solidFill></a:rPr><a:t>print(1)</a:t></a:r></a:p></p:txBody></p:sp><p:sp><p:nvSpPr><p:cNvPr id="27" name="TextBox 26"/><p:cNvSpPr txBox="1"/><p:nvPr/></p:nvSpPr><p:spPr><a:xfrm><a:off x="5374249" y="3641430"/><a:ext cx="908710" cy="369332"/></a:xfrm><a:prstGeom prst="rect"><a:avLst/></a:prstGeom><a:noFill/></p:spPr><p:txBody><a:bodyPr wrap="none" rtlCol="0"><a:spAutoFit/></a:bodyPr><a:lstStyle/><a:p><a:r><a:rPr lang="en-US" b="1" dirty="0"><a:solidFill><a:srgbClr val="FF0000"/></a:solidFill></a:rPr><a:t>print(3)</a:t></a:r></a:p></p:txBody></p:sp><p:sp><p:nvSpPr><p:cNvPr id="43" name="TextBox 42"/><p:cNvSpPr txBox="1"/><p:nvPr/></p:nvSpPr><p:spPr><a:xfrm><a:off x="7525310" y="408222"/><a:ext cx="3192734" cy="461665"/></a:xfrm><a:prstGeom prst="rect"><a:avLst/></a:prstGeom><a:noFill/></p:spPr><p:txBody><a:bodyPr wrap="none" rtlCol="0"><a:spAutoFit/></a:bodyPr><a:lstStyle/><a:p><a:r><a:rPr lang="en-US" sz="2400" dirty="0"/><a:t>Code this tree in Python</a:t></a:r></a:p></p:txBody></p:sp><p:cxnSp><p:nvCxnSpPr><p:cNvPr id="28" name="Straight Connector 27"/><p:cNvCxnSpPr/><p:nvPr/></p:nvCxnSpPr><p:spPr><a:xfrm><a:off x="3064897" y="4226733"/><a:ext cx="685799" cy="699247"/></a:xfrm><a:prstGeom prst="line"><a:avLst/></a:prstGeom></p:spPr><p:style><a:lnRef idx="1"><a:schemeClr val="accent1"/></a:lnRef><a:fillRef idx="0"><a:schemeClr val="accent1"/></a:fillRef><a:effectRef idx="0"><a:schemeClr val="accent1"/></a:effectRef><a:fontRef idx="minor"><a:schemeClr val="tx1"/></a:fontRef></p:style></p:cxnSp><p:sp><p:nvSpPr><p:cNvPr id="29" name="TextBox 28"/><p:cNvSpPr txBox="1"/><p:nvPr/></p:nvSpPr><p:spPr><a:xfrm><a:off x="3514967" y="4207024"/><a:ext cx="491225" cy="369332"/></a:xfrm><a:prstGeom prst="rect"><a:avLst/></a:prstGeom><a:noFill/></p:spPr><p:txBody><a:bodyPr wrap="none" rtlCol="0"><a:spAutoFit/></a:bodyPr><a:lstStyle/><a:p><a:r><a:rPr lang="en-US" dirty="0"><a:solidFill><a:srgbClr val="7030A0"/></a:solidFill></a:rPr><a:t>yes</a:t></a:r></a:p></p:txBody></p:sp><p:sp><p:nvSpPr><p:cNvPr id="30" name="TextBox 29"/><p:cNvSpPr txBox="1"/><p:nvPr/></p:nvSpPr><p:spPr><a:xfrm><a:off x="3373625" y="4843501"/><a:ext cx="908710" cy="369332"/></a:xfrm><a:prstGeom prst="rect"><a:avLst/></a:prstGeom><a:noFill/></p:spPr><p:txBody><a:bodyPr wrap="none" rtlCol="0"><a:spAutoFit/></a:bodyPr><a:lstStyle/><a:p><a:r><a:rPr lang="en-US" b="1" dirty="0"><a:solidFill><a:srgbClr val="FF0000"/></a:solidFill></a:rPr><a:t>print(4)</a:t></a:r></a:p></p:txBody></p:sp><p:sp><p:nvSpPr><p:cNvPr id="22" name="TextBox 21"><a:extLst><a:ext uri="{FF2B5EF4-FFF2-40B4-BE49-F238E27FC236}"><a16:creationId xmlns:a16="http://schemas.microsoft.com/office/drawing/2014/main" id="{1E18C399-6391-4824-8AED-BEC5DBC7B5A9}"/></a:ext></a:extLst></p:cNvPr><p:cNvSpPr txBox="1"/><p:nvPr/></p:nvSpPr><p:spPr><a:xfrm><a:off x="0" y="-22664"/><a:ext cx="1215397" cy="1323439"/></a:xfrm><a:prstGeom prst="rect"><a:avLst/></a:prstGeom><a:noFill/></p:spPr><p:txBody><a:bodyPr wrap="none" rtlCol="0"><a:spAutoFit/></a:bodyPr><a:lstStyle/><a:p><a:r><a:rPr lang="en-US" sz="8000" dirty="0"/><a:t>#3</a:t></a:r></a:p></p:txBody></p:sp><p:sp><p:nvSpPr><p:cNvPr id="2" name="TextBox 1"/><p:cNvSpPr txBox="1"/><p:nvPr/></p:nvSpPr><p:spPr><a:xfrm><a:off x="7546914" y="1352814"/><a:ext cx="3762103" cy="4832092"/></a:xfrm><a:prstGeom prst="rect"><a:avLst/></a:prstGeom><a:noFill/></p:spPr><p:txBody><a:bodyPr wrap="square" rtlCol="0"><a:spAutoFit/></a:bodyPr><a:lstStyle/><a:p><a:r><a:rPr lang="en-US" sz="2800" dirty="0" smtClean="0"><a:solidFill><a:srgbClr val="FF0000"/></a:solidFill></a:rPr><a:t>X = 0 </a:t></a:r></a:p><a:p><a:r><a:rPr lang="en-US" sz="2800" dirty="0" smtClean="0"><a:solidFill><a:srgbClr val="FF0000"/></a:solidFill></a:rPr><a:t>Y = 0</a:t></a:r></a:p><a:p><a:r><a:rPr lang="en-US" sz="2800" dirty="0" smtClean="0"><a:solidFill><a:srgbClr val="FF0000"/></a:solidFill></a:rPr><a:t>Z = 0 </a:t></a:r></a:p><a:p><a:r><a:rPr lang="en-US" sz="2800" dirty="0" smtClean="0"><a:solidFill><a:srgbClr val="FF0000"/></a:solidFill></a:rPr><a:t>If x == 3 :</a:t></a:r></a:p><a:p><a:r><a:rPr lang="en-US" sz="2800" dirty="0"><a:solidFill><a:srgbClr val="FF0000"/></a:solidFill></a:rPr><a:t>	</a:t></a:r><a:r><a:rPr lang="en-US" sz="2800" dirty="0" smtClean="0"><a:solidFill><a:srgbClr val="FF0000"/></a:solidFill></a:rPr><a:t>if y &gt;3:</a:t></a:r></a:p><a:p><a:r><a:rPr lang="en-US" sz="2800" dirty="0"><a:solidFill><a:srgbClr val="FF0000"/></a:solidFill></a:rPr><a:t>	</a:t></a:r><a:r><a:rPr lang="en-US" sz="2800" dirty="0" smtClean="0"><a:solidFill><a:srgbClr val="FF0000"/></a:solidFill></a:rPr><a:t>	print(3)</a:t></a:r></a:p><a:p><a:r><a:rPr lang="en-US" sz="2800" dirty="0" err="1"><a:solidFill><a:srgbClr val="FF0000"/></a:solidFill></a:rPr><a:t>e</a:t></a:r><a:r><a:rPr lang="en-US" sz="2800" dirty="0" err="1" smtClean="0"><a:solidFill><a:srgbClr val="FF0000"/></a:solidFill></a:rPr><a:t>lif</a:t></a:r><a:r><a:rPr lang="en-US" sz="2800" dirty="0" smtClean="0"><a:solidFill><a:srgbClr val="FF0000"/></a:solidFill></a:rPr><a:t>  y &gt;3 and z &lt;10 :</a:t></a:r></a:p><a:p><a:r><a:rPr lang="en-US" sz="2800" dirty="0"><a:solidFill><a:srgbClr val="FF0000"/></a:solidFill></a:rPr><a:t>	</a:t></a:r><a:r><a:rPr lang="en-US" sz="2800" dirty="0" smtClean="0"><a:solidFill><a:srgbClr val="FF0000"/></a:solidFill></a:rPr><a:t>print(4)</a:t></a:r></a:p><a:p><a:r><a:rPr lang="en-US" sz="2800" dirty="0"><a:solidFill><a:srgbClr val="FF0000"/></a:solidFill></a:rPr><a:t>e</a:t></a:r><a:r><a:rPr lang="en-US" sz="2800" dirty="0" smtClean="0"><a:solidFill><a:srgbClr val="FF0000"/></a:solidFill></a:rPr><a:t>lse:</a:t></a:r></a:p><a:p><a:r><a:rPr lang="en-US" sz="2800" dirty="0"><a:solidFill><a:srgbClr val="FF0000"/></a:solidFill></a:rPr><a:t>	</a:t></a:r><a:r><a:rPr lang="en-US" sz="2800" dirty="0" smtClean="0"><a:solidFill><a:srgbClr val="FF0000"/></a:solidFill></a:rPr><a:t>print(1)</a:t></a:r></a:p><a:p><a:endParaRPr lang="en-US" sz="2800" dirty="0"><a:solidFill><a:srgbClr val="FF0000"/></a:solidFill></a:endParaRPr></a:p></p:txBody></p:sp></p:spTree><p:extLst><p:ext uri="{BB962C8B-B14F-4D97-AF65-F5344CB8AC3E}"><p14:creationId xmlns:p14="http://schemas.microsoft.com/office/powerpoint/2010/main" val="3494505645"/></p:ext></p:extLst></p:cSld><p:clrMapOvr><a:masterClrMapping/></p:clrMapOvr></p:sld>